kuorra/__init__.py
kuorra/__main__.py
kuorra/api_generator.py
kuorra/controller_generator.py
kuorra/kuorra.py
kuorra/model_generator.py
kuorra/view_generator.py
kuorra/controllers/__init__.py
kuorra/controllers/config.py
kuorra/controllers/delete.py
kuorra/controllers/edit.py
kuorra/controllers/index.py
kuorra/controllers/insert.py
kuorra/controllers/url.md
kuorra/controllers/view.py
kuorra/mvc/Procfile
kuorra/mvc/Readme.md
kuorra/mvc/app.py
kuorra/mvc/requirements.txt
kuorra/mvc/runtime.txt
kuorra/mvc/application/__init__.py
kuorra/mvc/application/api/__init__.py
kuorra/mvc/application/api/products/__init__.py
kuorra/mvc/application/api/products/api_products.py
kuorra/mvc/application/api/products/config.py
kuorra/mvc/application/controllers/__init__.py
kuorra/mvc/application/controllers/products/__init__.py
kuorra/mvc/application/controllers/products/config.py
kuorra/mvc/application/controllers/products/delete.py
kuorra/mvc/application/controllers/products/edit.py
kuorra/mvc/application/controllers/products/index.py
kuorra/mvc/application/controllers/products/insert.py
kuorra/mvc/application/controllers/products/view.py
kuorra/mvc/application/models/__init__.py
kuorra/mvc/application/models/config.py
kuorra/mvc/application/models/model_products.py
kuorra/mvc/application/views/__init__.py
kuorra/mvc/application/views/products/__init__.py
kuorra/mvc/application/views/products/delete.html
kuorra/mvc/application/views/products/edit.html
kuorra/mvc/application/views/products/index.html
kuorra/mvc/application/views/products/insert.html
kuorra/mvc/application/views/products/master.html
kuorra/mvc/application/views/products/view.html
kuorra/mvc/data/schema.sql
kuorra/mvc/ssl/server.crt
kuorra/mvc/ssl/server.csr
kuorra/mvc/ssl/server.key
kuorra/mvc/static/favicon.ico
kuorra/mvc/static/index.html
kuorra/mvc/static/css/bootstrap.css
kuorra/mvc/static/css/dataTables.bootstrap.min.css
kuorra/mvc/static/css/index.html
kuorra-0.7.2.2.dist-info/DESCRIPTION.rst
kuorra-0.7.2.2.dist-info/METADATA
kuorra-0.7.2.2.dist-info/RECORD
kuorra-0.7.2.2.dist-info/WHEEL
kuorra-0.7.2.2.dist-info/entry_points.txt
kuorra-0.7.2.2.dist-info/metadata.json
kuorra-0.7.2.2.dist-info/top_level.txt
