Metadata-Version: 2.0
Name: kuorra
Version: 0.7.2.2
Summary: web.py scaffolding tool, generate MVC code (Models, Views, Controllers and RESTfull API) from command line
Home-page: https://salvadorhm.github.io/kuorra
Author: Salvador Hernandez Mendoza
Author-email: salvadorhm@gmail.com
License: GPLv3
Download-URL: https://salvadorhm.github.io/kuorra
Keywords: scaffold mvc web.py mysql heroku bootstrap jquery ssl api restful
Platform: UNKNOWN
Classifier: Development Status :: 4 - Beta
Classifier: Intended Audience :: Developers
Classifier: Topic :: Software Development
Classifier: License :: OSI Approved :: GNU General Public License v3 (GPLv3)
Classifier: Programming Language :: Python :: 2.7
Requires-Dist: MySQL-python (==1.2.5)
Requires-Dist: asn1crypto (>=0.21.0)
Requires-Dist: cffi (>=1.7)
Requires-Dist: cryptography (>=1.3.4)
Requires-Dist: idna (>=2.1)
Requires-Dist: pyOpenSSL (==16.2.0)
Requires-Dist: six (>=1.5.2)
Requires-Dist: web.py (==0.38)
